PySimpleNginx/__init__.py
PySimpleNginx/config.py
PySimpleNginx/control.py
PySimpleNginx/utils.py
PySimpleNginx-0.1.0.dist-info/METADATA
PySimpleNginx-0.1.0.dist-info/WHEEL
PySimpleNginx-0.1.0.dist-info/top_level.txt
PySimpleNginx-0.1.0.dist-info/RECORD
