Metadata-Version: 2.1
Name: PySimpleNginx
Version: 0.1.0
Summary: A simple nginx config and control module
Home-page: https://github.com/stemsky/PySimpleNginx.git
Author: stemsky
Author-email: UNKNOWN
License: UNKNOWN
Platform: UNKNOWN
